MANIFEST.in
README.md
setup.py
fil3s/.version.py
fil3s/__init__.py
fil3s.egg-info/PKG-INFO
fil3s.egg-info/SOURCES.txt
fil3s.egg-info/dependency_links.txt
fil3s.egg-info/not-zip-safe
fil3s.egg-info/requires.txt
fil3s.egg-info/top_level.txt
fil3s/classes/__init__.py
fil3s/classes/cli/__init__.py
fil3s/classes/code/__init__.py
fil3s/classes/code/execute.py
fil3s/classes/color/__init__.py
fil3s/classes/config/__init__.py
fil3s/classes/defaults/__init__.py
fil3s/classes/env/__init__.py
fil3s/classes/exceptions/__init__.py
fil3s/classes/files/__init__.py
fil3s/classes/objects/__init__.py
fil3s/classes/requests/__init__.py
fil3s/classes/response/__init__.py
fil3s/classes/utils/__init__.py
fil3s/classes/utils/copycats.py
fil3s/js/fil3s.html