Metadata-Version: 1.0
Name: fil3s
Version: 2.15.8
Summary: Some description.
Home-page: http://github.com/vandenberghinc/fil3s
Author: Daan van den Bergh
Author-email: vandenberghinc.contact@gmail.com
License: MIT
Platform: UNKNOWN
